laboro/__init__.py
laboro/__main__.py
laboro/config/__init__.py
laboro/config/manager/__init__.py
laboro/config/manager/schema/__init__.py
laboro/config/manager/schema/main.yml
laboro/config/manager/schema/workflow.yml
laboro/context/__init__.py
laboro/context/action/__init__.py
laboro/context/method/__init__.py
laboro/context/step/__init__.py
laboro/context/store/__init__.py
laboro/context/workflow/__init__.py
laboro/crypto/__init__.py
laboro/error/__init__.py
laboro/error/handler/__init__.py
laboro/history/__init__.py
laboro/interactive/__init__.py
laboro/interactive/decrypt.py
laboro/interactive/encrypt.py
laboro/logger/__init__.py
laboro/logger/manager/__init__.py
laboro/logic/__init__.py
laboro/logic/parser/__init__.py
laboro/logic/processor/__init__.py
laboro/module/__init__.py
laboro/module/manager/__init__.py
laboro/module/schema/__init__.py
laboro/module/schema/instance.yml
laboro/validator/__init__.py
laboro/vault/__init__.py
laboro/workflow/__init__.py
laboro/workflow/action/__init__.py
laboro/workflow/method/__init__.py
laboro/workflow/step/__init__.py
laboro/workspace/__init__.py
laboro-0.2.9.dist-info/LICENSE
laboro-0.2.9.dist-info/METADATA
laboro-0.2.9.dist-info/WHEEL
laboro-0.2.9.dist-info/top_level.txt
laboro-0.2.9.dist-info/RECORD
