Metadata-Version: 2.1
Name: laboro
Version: 0.2.9
Summary: The Laboro workflow framework
Home-page: https://codeberg.org/laboro/laboro
Author: Michaël Costa
Author-email: michael.costa@mcos.nc
Project-URL: Bug Tracker, https://codeberg.org/laboro/laboro/issues
Classifier: Programming Language :: Python :: 3
Classifier: License :: OSI Approved :: MIT License
Classifier: Operating System :: OS Independent
Classifier: Topic :: Software Development :: Libraries :: Application Frameworks
Classifier: Intended Audience :: Developers
Classifier: Intended Audience :: System Administrators
Classifier: Environment :: Console
Classifier: Development Status :: 4 - Beta
Requires-Python: >=3.9
License-File: LICENSE
Requires-Dist: jsonpath-python (>=1.0.6)
Requires-Dist: PyYAML (>=5.4.1)
Requires-Dist: pyyaml-include (>=1.3)
Requires-Dist: prettytable (>=2.1.0)
Requires-Dist: coloredlogs (>=15.0.1)
Requires-Dist: jsonschema (>=3.2.0)
Requires-Dist: asteval (>=0.9.27)
Requires-Dist: cryptography (>=36.0.1)
Provides-Extra: dev
Requires-Dist: flake8 (>=4.0.1) ; extra == 'dev'
Requires-Dist: pylint (>=2.12.2) ; extra == 'dev'
Requires-Dist: yamllint (>=1.26.0) ; extra == 'dev'
Requires-Dist: autopep8 (>=1.6.0) ; extra == 'dev'
Requires-Dist: Jinja2 ; extra == 'dev'
Requires-Dist: Sphinx (>=4.5.0) ; extra == 'dev'
Requires-Dist: sphinx-rtd-theme (>=1.0.0) ; extra == 'dev'
Requires-Dist: sphinxcontrib-napoleon (>=0.7) ; extra == 'dev'
Requires-Dist: auto-changelog (>=0.5.3) ; extra == 'dev'
Requires-Dist: pylama (>=8.3.8) ; extra == 'dev'
Provides-Extra: tests
Requires-Dist: pytest (>=7.1.2) ; extra == 'tests'
Requires-Dist: pytest-cov (>=3.0.0) ; extra == 'tests'
Requires-Dist: laboro-demo (>=0.0.23) ; extra == 'tests'
